cnholiday/__init__.py
cnholiday/data.json
cnholiday-0.2.0.dist-info/WHEEL
cnholiday-0.2.0.dist-info/METADATA
cnholiday-0.2.0.dist-info/RECORD
