Metadata-Version: 2.1
Name: cnholiday
Version: 0.2.0
Summary: 查询某天是否放假
Home-page: https://github.com/ringsaturn/cnholiday
Author: ringsaturn
Author-email: ringsaturn.me@gmail.com
Requires-Python: >=3.6,<4.0
Classifier: Programming Language :: Python :: 3
Classifier: Programming Language :: Python :: 3.6
Classifier: Programming Language :: Python :: 3.7
Classifier: Programming Language :: Python :: 3.8
Classifier: Programming Language :: Python :: 3.9
Project-URL: Documentation, https://ringsaturn.github.io/cnholiday/
Project-URL: Repository, https://github.com/ringsaturn/cnholiday
